MANIFEST.in
README.md
setup.py
scripts/all-the-graphs
scripts/build-graphs
tinc_graphs/Availability.py
tinc_graphs/BackwardsReader.py
tinc_graphs/Geo.py
tinc_graphs/Graph.py
tinc_graphs/Log2JSON.py
tinc_graphs/Services.py
tinc_graphs/Supernodes.py
tinc_graphs/__init__.py
tinc_graphs.egg-info/PKG-INFO
tinc_graphs.egg-info/SOURCES.txt
tinc_graphs.egg-info/dependency_links.txt
tinc_graphs.egg-info/entry_points.txt
tinc_graphs.egg-info/requires.txt
tinc_graphs.egg-info/top_level.txt
tinc_graphs/static/external/index.html
tinc_graphs/static/external/css/graphs.css
tinc_graphs/static/internal/index.html
tinc_graphs/static/internal/map.html
tinc_graphs/static/internal/css/graphs.css