Metadata-Version: 1.1
Name: tinc-graphs
Version: 0.3.10
Summary: Create Graphs from tinc Stats
Home-page: http://krebsco.de/
Author: krebs
Author-email: spam@krebsco.de
License: WTFPL
Download-URL: https://pypi.python.org/pypi/tinc_graphs/
Platform: UNKNOWN
Classifier: Intended Audience :: Developers
Classifier: Natural Language :: English
Classifier: Operating System :: POSIX :: Linux
Classifier: Development Status :: 3 - Alpha
Classifier: Programming Language :: Python
Classifier: Programming Language :: Python :: 2.7
Classifier: Programming Language :: Python :: 3
Classifier: Programming Language :: Python :: 3.4
Classifier: Programming Language :: Python :: Implementation :: CPython
